disnake_plugins/__init__.py
disnake_plugins/async_utils.py
disnake_plugins/plugin.py
disnake_ext_plugins-0.3.0.dist-info/LICENSE
disnake_ext_plugins-0.3.0.dist-info/METADATA
disnake_ext_plugins-0.3.0.dist-info/WHEEL
disnake_ext_plugins-0.3.0.dist-info/entry_points.txt
disnake_ext_plugins-0.3.0.dist-info/RECORD
