Metadata-Version: 2.1
Name: disnake-ext-plugins
Version: 0.3.0
Summary: An extension for disnake providing a robust alternative to cogs.
Home-page: https://github.com/Chromosomologist/disnake-ext-plugins
License: MIT
Keywords: disnake,disnake.ext,discord,cogs
Author: Chromosomologist
Author-email: chromosomologist@gmail.com
Requires-Python: >=3.8,<4.0
Classifier: Development Status :: 3 - Alpha
Classifier: Intended Audience :: Developers
Classifier: License :: OSI Approved :: MIT License
Classifier: Natural Language :: English
Classifier: Operating System :: OS Independent
Classifier: Programming Language :: Python :: 3
Classifier: Programming Language :: Python :: 3.8
Classifier: Programming Language :: Python :: 3.9
Classifier: Programming Language :: Python :: 3.10
Classifier: Programming Language :: Python :: 3.11
Classifier: Programming Language :: Python :: 3.12
Classifier: Topic :: Internet
Classifier: Topic :: Software Development :: Libraries
Classifier: Topic :: Software Development :: Libraries :: Python Modules
Classifier: Topic :: Utilities
Classifier: Typing :: Typed
Requires-Dist: disnake (>=2.8,<3.0)
Project-URL: Repository, https://github.com/Chromosomologist/disnake-ext-plugins
